aioclient.py
aioclient-0.2.2.dist-info/licenses/LICENSE.md
aioclient-0.2.2.dist-info/METADATA
aioclient-0.2.2.dist-info/WHEEL
aioclient-0.2.2.dist-info/top_level.txt
aioclient-0.2.2.dist-info/RECORD
